properscoring/__init__.py
properscoring/_brier.py
properscoring/_crps.py
properscoring/_gufuncs.py
properscoring/_utils.py
properscoring/thresholds.py
properscoring/tests/__init__.py
properscoring/tests/test_brier.py
properscoring/tests/test_crps.py
properscoring/tests/test_utils.py
properscoring-0.1.dist-info/DESCRIPTION.rst
properscoring-0.1.dist-info/METADATA
properscoring-0.1.dist-info/RECORD
properscoring-0.1.dist-info/WHEEL
properscoring-0.1.dist-info/metadata.json
properscoring-0.1.dist-info/top_level.txt
